Workbook

Sheet Financial Projection
A2: Prayat (ScamSim) — 3-Year Financial Projection
A3: Currency: USD. Two B2C tiers — Standard $1.50/month and Premium $2.50/month — plus a school licence. Blue text on yellow = editable assumption; black = formula; green = link to another sheet.
A5: Section | B5: Assumption | C5: Formula / reference | D5: Year 1 | E5: Year 2 | F5: Year 3
A6: Pricing
B7: Standard subscription fee (per month) | C7: Tier 1 — individual, all modes, score tracking | D7: 1.5 | E7: 1.5 | F7: 1.5
B8: Premium subscription fee (per month) | C8: Tier 2 — family plan (up to 4), parent dashboard, reports | D8: 2.5 | E8: 2.5 | F8: 2.5
B9: School licence fee (per student per month) | C9: B2B — per-student licence, billed to the school | D9: 1.5 | E9: 1.5 | F9: 1.5
A11: Standard tier — customers
B12: Beginning Standard subscribers | C12: Year 1 input; later years link to prior ending | D12: =0 | E12: =D17 | F12: =E17
B13: New Standard subscribers | C13: Acquisition assumption — parents, students, young adults (team estimate) | D13: 800 | E13: 2500 | F13: 6000
B14: Monthly churn — Standard | C14: Subscribers lost / subscribers at start of month (team estimate, price-sensitive consumer app) | D14: 0.04 | E14: 0.03 | F14: 0.025
B15: Annual churn — Standard | C15: 1 - (1 - monthly churn)^12 | D15: =1-(1-D14)^12 | E15: =1-(1-E14)^12 | F15: =1-(1-F14)^12
B16: Standard subscribers lost | C16: (Beginning + 50% of new) x annual churn | D16: =(D12+D13*50%)*D15 | E16: =(E12+E13*50%)*E15 | F16: =(F12+F13*50%)*F15
B17: Ending Standard subscribers | C17: Beginning + new - lost | D17: =D12+D13-D16 | E17: =E12+E13-E16 | F17: =F12+F13-F16
B18: Average Standard subscribers | C18: (Beginning + ending) / 2 | D18: =(D12+D17)/2 | E18: =(E12+E17)/2 | F18: =(F12+F17)/2
A20: Premium tier — customers
B21: Beginning Premium subscribers | C21: Year 1 input; later years link to prior ending | D21: =0 | E21: =D26 | F21: =E26
B22: New Premium subscribers | C22: Acquisition assumption — families, adult children buying for parents (team estimate) | D22: 200 | E22: 700 | F22: 2000
B23: Monthly churn — Premium | C23: Family plans churn less than individuals (team estimate) | D23: 0.03 | E23: 0.025 | F23: 0.02
B24: Annual churn — Premium | C24: 1 - (1 - monthly churn)^12 | D24: =1-(1-D23)^12 | E24: =1-(1-E23)^12 | F24: =1-(1-F23)^12
B25: Premium subscribers lost | C25: (Beginning + 50% of new) x annual churn | D25: =(D21+D22*50%)*D24 | E25: =(E21+E22*50%)*E24 | F25: =(F21+F22*50%)*F24
B26: Ending Premium subscribers | C26: Beginning + new - lost | D26: =D21+D22-D25 | E26: =E21+E22-E25 | F26: =F21+F22-F25
B27: Average Premium subscribers | C27: (Beginning + ending) / 2 | D27: =(D21+D26)/2 | E27: =(E21+E26)/2 | F27: =(F21+F26)/2
A29: School licence — students
B30: Licensed students (average over the year) | C30: Pilot 1 school in Y1 (deck draft), then 4 and 10 schools (team estimate) | D30: 200 | E30: 800 | F30: 2000
A32: All paying users
B33: Ending B2C subscribers (Standard + Premium) | C33: Ending Standard + ending Premium | D33: =D17+D26 | E33: =E17+E26 | F33: =F17+F26
B34: Average paying users (B2C + school) | C34: Average Standard + average Premium + licensed students | D34: =D18+D27+D30 | E34: =E18+E27+E30 | F34: =F18+F27+F30
B35: Ending MRR | C35: Ending Standard x $1.50 + ending Premium x $2.50 + students x school fee | D35: =D17*D7+D26*D8+D30*D9 | E35: =E17*E7+E26*E8+E30*E9 | F35: =F17*F7+F26*F8+F30*F9
B36: Ending ARR | C36: MRR x 12 | D36: =D35*12 | E36: =E35*12 | F36: =F35*12
A38: Sales Revenue
B39: Standard revenue | C39: Average Standard subscribers x $1.50 x 12 | D39: =D18*D7*12 | E39: =E18*E7*12 | F39: =F18*F7*12
B40: Premium revenue | C40: Average Premium subscribers x $2.50 x 12 | D40: =D27*D8*12 | E40: =E27*E8*12 | F40: =F27*F8*12
B41: School licence revenue | C41: Licensed students x school fee x 12 | D41: =D30*D9*12 | E41: =E30*E9*12 | F41: =F30*F9*12
B42: Total recognized revenue | C42: Standard + Premium + school | D42: =SUM(D39:D41) | E42: =SUM(E39:E41) | F42: =SUM(F39:F41)
B43: Revenue growth | C43: Current year / prior year - 1 | D43: ="" | E43: =E42/D42-1 | F43: =F42/E42-1
B44: Blended ARPU per user per month | C44: Total revenue / average paying users / 12 | D44: =IF(D34=0,0,D42/D34/12) | E44: =IF(E34=0,0,E42/E34/12) | F44: =IF(F34=0,0,F42/F34/12)
B45: Premium share of B2C subscribers | C45: Ending Premium / ending B2C | D45: =IF(D33=0,0,D26/D33) | E45: =IF(E33=0,0,E26/E33) | F45: =IF(F33=0,0,F26/F33)
A47: COGS / Service Delivery
B48: Hosting cost per user/month | C48: Render + SQLite today; scales down per user (team estimate) | D48: 0.04 | E48: 0.03 | F48: 0.025
B49: AI dialogue cost per user/month | C49: DeepSeek rewrite ~US$0.0002/stage x ~100 stages/user/month (measured in dev) | D49: 0.02 | E49: 0.015 | F49: 0.01
B50: Customer support cost per user/month | C50: Telegram support channel, part-time (team estimate) | D50: 0.05 | E50: 0.05 | F50: 0.04
B51: Payment processing fee rate | C51: KHQR / Wing / ABA merchant fee as % of revenue (assumption) | D51: 0.03 | E51: 0.03 | F51: 0.03
B52: Payment fee per user/month | C52: Blended ARPU x payment fee rate | D52: =D44*D51 | E52: =E44*E51 | F52: =F44*F51
B53: Total COGS per user/month | C53: Hosting + AI + support + payment fee | D53: =D48+D49+D50+D52 | E53: =E48+E49+E50+E52 | F53: =F48+F49+F50+F52
B54: Annual COGS | C54: Average paying users x COGS per user/month x 12 | D54: =D34*D53*12 | E54: =E34*E53*12 | F54: =F34*F53*12
B56: Gross profit | C56: Revenue - COGS | D56: =D42-D54 | E56: =E42-E54 | F56: =F42-F54
B57: Gross margin | C57: Gross profit / revenue | D57: =IF(D42=0,0,D56/D42) | E57: =IF(E42=0,0,E56/E42) | F57: =IF(F42=0,0,F56/F42)
A59: Sales & Marketing
B60: Marketing spend | C60: Facebook/TikTok ads, school events, Khmer creators (team estimate) | D60: 3000 | E60: 9000 | F60: 20000
B61: Referral & partner incentives | C61: Free-month referrals, school-visit costs (team estimate) | D61: 600 | E61: 2000 | F61: 5000
B62: Total sales and marketing | C62: Marketing + referral incentives | D62: =D60+D61 | E62: =E60+E61 | F62: =F60+F61
B63: CAC (per new B2C subscriber) | C63: Sales and marketing / (new Standard + new Premium) | D63: =IF((D13+D22)=0,0,D62/(D13+D22)) | E63: =IF((E13+E22)=0,0,E62/(E13+E22)) | F63: =IF((F13+F22)=0,0,F62/(F13+F22))
B64: CAC payback (months) | C64: CAC / (blended ARPU - COGS per user/month) | D64: =IF((D44-D53)<=0,0,D63/(D44-D53)) | E64: =IF((E44-E53)<=0,0,E63/(E44-E53)) | F64: =IF((F44-F53)<=0,0,F63/(F44-F53))
A66: Operating Expenses
B67: Product development payroll | C67: Founders part-time Y1, first hires Y2-Y3 (team estimate) | D67: 6000 | E67: 18000 | F67: 36000
B68: Content writing & Khmer review | C68: New scenarios monthly + over-45 reviewer per AUTHORING.md (team estimate) | D68: 1500 | E68: 3000 | F68: 6000
B69: Founder / admin salary | C69: Cash cost only (team estimate) | D69: 3000 | E69: 6000 | F69: 12000
B70: Software tools | C70: Domain, design tools, DeepSeek/API minimums (team estimate) | D70: 600 | E70: 1200 | F70: 2400
B71: Office, legal and accounting | C71: Company registration, accounting (team estimate) | D71: 500 | E71: 1500 | F71: 3000
B72: Total operating expenses | C72: Sum of operating expenses excluding sales and marketing | D72: =SUM(D67:D71) | E72: =SUM(E67:E71) | F72: =SUM(F67:F71)
A74: Capital & Depreciation
B75: Depreciation and amortization | C75: Non-cash (team estimate) | D75: 500 | E75: 800 | F75: 1200
B76: Capital expenditure | C76: Laptops, test phones (team estimate) | D76: 1500 | E76: 2000 | F76: 3000
A78: Profitability
B79: EBITDA | C79: Gross profit - sales and marketing - operating expenses | D79: =D56-D62-D72 | E79: =E56-E62-E72 | F79: =F56-F62-F72
B80: EBITDA margin | C80: EBITDA / revenue | D80: =IF(D42=0,0,D79/D42) | E80: =IF(E42=0,0,E79/E42) | F80: =IF(F42=0,0,F79/F42)
B81: EBIT / operating profit | C81: EBITDA - depreciation and amortization | D81: =D79-D75 | E81: =E79-E75 | F81: =F79-F75
B82: Tax rate | C82: Cambodia corporate income tax 20% (General Department of Taxation) | D82: 0.2 | E82: 0.2 | F82: 0.2
B83: Income tax | C83: MAX(0, EBIT x tax rate) | D83: =MAX(0,D81*D82) | E83: =MAX(0,E81*E82) | F83: =MAX(0,F81*F82)
B84: Net profit | C84: EBIT - income tax | D84: =D81-D83 | E84: =E81-E83 | F84: =F81-F83
B85: Net profit margin | C85: Net profit / revenue | D85: =IF(D42=0,0,D84/D42) | E85: =IF(E42=0,0,E84/E42) | F85: =IF(F42=0,0,F84/F42)
A87: Break-Even
B88: Monthly gross profit per user | C88: Blended ARPU - COGS per user/month | D88: =D44-D53 | E88: =E44-E53 | F88: =F44-F53
B89: Monthly fixed cash cost | C89: (Sales and marketing + operating expenses) / 12 | D89: =(D62+D72)/12 | E89: =(E62+E72)/12 | F89: =(F62+F72)/12
B90: Break-even paying users | C90: Fixed cost / monthly gross profit per user | D90: =IF(D88<=0,0,D89/D88) | E90: =IF(E88<=0,0,E89/E88) | F90: =IF(F88<=0,0,F89/F88)
B91: Break-even MRR | C91: Break-even users x blended ARPU | D91: =D90*D44 | E91: =E90*E44 | F91: =F90*F44
B92: Break-even ARR | C92: Break-even MRR x 12 | D92: =D91*12 | E92: =E91*12 | F92: =F91*12
A94: Cash Flow
B95: Beginning cash | C95: Year 1 input (competition prize / founder funds); later years link to prior ending cash | D95: 15000 | E95: =D98 | F95: =E98
B96: Operating cash flow | C96: Net profit + depreciation and amortization | D96: =D84+D75 | E96: =E84+E75 | F96: =F84+F75
B97: Free cash flow | C97: Operating cash flow - capital expenditure | D97: =D96-D76 | E97: =E96-E76 | F97: =F96-F76
B98: Ending cash | C98: Beginning cash + free cash flow | D98: =D95+D97 | E98: =E95+E97 | F98: =F95+F97
B99: Monthly burn rate | C99: If free cash flow is negative, ABS(free cash flow) / 12 | D99: =IF(D97<0,ABS(D97)/12,0) | E99: =IF(E97<0,ABS(E97)/12,0) | F99: =IF(F97<0,ABS(F97)/12,0)
B100: Runway (months) | C100: Ending cash / monthly burn when burning cash | D100: =IF(D99>0,D98/D99,"") | E100: =IF(E99>0,E98/E99,"") | F100: =IF(F99>0,F98/F99,"")
A102: Investor Ratios
B103: Customer lifetime — Standard (months) | C103: 1 / monthly churn | D103: =1/D14 | E103: =1/E14 | F103: =1/F14
B104: Customer lifetime — Premium (months) | C104: 1 / monthly churn | D104: =1/D23 | E104: =1/E23 | F104: =1/F23
B105: LTV — Standard | C105: Fee x gross margin / monthly churn | D105: =D7*D57/D14 | E105: =E7*E57/E14 | F105: =F7*F57/F14
B106: LTV — Premium | C106: Fee x gross margin / monthly churn | D106: =D8*D57/D23 | E106: =E8*E57/E23 | F106: =F8*F57/F23
B107: LTV:CAC — Standard | C107: LTV / CAC | D107: =IF(D63=0,0,D105/D63) | E107: =IF(E63=0,0,E105/E63) | F107: =IF(F63=0,0,F105/F63)
B108: LTV:CAC — Premium | C108: LTV / CAC | D108: =IF(D63=0,0,D106/D63) | E108: =IF(E63=0,0,E106/E63) | F108: =IF(F63=0,0,F106/F63)
A110: Notes & sources
A111: 1. Prices ($1.50 Standard, $2.50 Premium, $1.50/student school licence) are the team's pricing decision for Cambodia's price-sensitive market; the pitch deck's $3/$5 draft was lowered per its own validation note.
A112: 2. Subscriber, churn, marketing and payroll figures are team estimates for a pre-revenue startup — replace with survey/pilot data before pitching. Judges will ask how each number was obtained.
A113: 3. AI dialogue cost: DeepSeek 'deepseek-flash' measured at roughly US$0.0002 per rewritten stage during development; the feature is optional (PRAYAT_AI flag) so this line can be set to 0.
A114: 4. Payment fee 3% is an assumption for KHQR / Wing / ABA merchant collection; confirm the actual merchant rate with the provider.
A115: 5. Tax rate 20% is Cambodia's standard corporate income tax (General Department of Taxation). Losses are not carried forward in this simple model.
A116: 6. Year 1 beginning cash of $15,000 assumes competition prize money plus founder contribution — edit to your real figure.

Sheet Summary
A1: Prayat — 3-year summary
A2: Every cell links to the Financial Projection sheet (green). Edit assumptions there, not here.
A4: Metric | B4: Year 1 | C4: Year 2 | D4: Year 3
A5: Ending B2C subscribers | B5: ='Financial Projection'!D33 | C5: ='Financial Projection'!E33 | D5: ='Financial Projection'!F33
A6: Licensed students | B6: ='Financial Projection'!D30 | C6: ='Financial Projection'!E30 | D6: ='Financial Projection'!F30
A7: Ending MRR | B7: ='Financial Projection'!D35 | C7: ='Financial Projection'!E35 | D7: ='Financial Projection'!F35
A8: Total revenue | B8: ='Financial Projection'!D42 | C8: ='Financial Projection'!E42 | D8: ='Financial Projection'!F42
A9: Revenue growth | B9: ='Financial Projection'!D43 | C9: ='Financial Projection'!E43 | D9: ='Financial Projection'!F43
A10: Gross margin | B10: ='Financial Projection'!D57 | C10: ='Financial Projection'!E57 | D10: ='Financial Projection'!F57
A11: Sales and marketing | B11: ='Financial Projection'!D62 | C11: ='Financial Projection'!E62 | D11: ='Financial Projection'!F62
A12: Operating expenses | B12: ='Financial Projection'!D72 | C12: ='Financial Projection'!E72 | D12: ='Financial Projection'!F72
A13: EBITDA | B13: ='Financial Projection'!D79 | C13: ='Financial Projection'!E79 | D13: ='Financial Projection'!F79
A14: Net profit | B14: ='Financial Projection'!D84 | C14: ='Financial Projection'!E84 | D14: ='Financial Projection'!F84
A15: Ending cash | B15: ='Financial Projection'!D98 | C15: ='Financial Projection'!E98 | D15: ='Financial Projection'!F98
A16: Break-even paying users | B16: ='Financial Projection'!D90 | C16: ='Financial Projection'!E90 | D16: ='Financial Projection'!F90
A17: CAC | B17: ='Financial Projection'!D63 | C17: ='Financial Projection'!E63 | D17: ='Financial Projection'!F63
A18: LTV:CAC — Standard | B18: ='Financial Projection'!D107 | C18: ='Financial Projection'!E107 | D18: ='Financial Projection'!F107
A19: LTV:CAC — Premium | B19: ='Financial Projection'!D108 | C19: ='Financial Projection'!E108 | D19: ='Financial Projection'!F108
A21: Year 3 / Year 1 revenue | B21: =IF(B8=0,0,D8/B8)
A22: Average annual revenue growth | B22: =AVERAGE(C9:D9)
